ttstokenizer/__init__.py
ttstokenizer/checkpoint20.npz
ttstokenizer/cmudict.dict
ttstokenizer/custom.dict
ttstokenizer/expand.py
ttstokenizer/g2p.py
ttstokenizer/homographs.en
ttstokenizer/tokenizer.py
ttstokenizer-1.1.0.dist-info/LICENSE.txt
ttstokenizer-1.1.0.dist-info/METADATA
ttstokenizer-1.1.0.dist-info/WHEEL
ttstokenizer-1.1.0.dist-info/top_level.txt
ttstokenizer-1.1.0.dist-info/RECORD
