Metadata-Version: 2.1
Name: ttstokenizer
Version: 1.1.0
Summary: Tokenizer for Text to Speech (TTS) models
Home-page: https://github.com/neuml/ttstokenizer
License: Apache 2.0: http://www.apache.org/licenses/LICENSE-2.0
License-File: LICENSE.txt
Requires-Dist: anyascii (>=0.3.1)
Requires-Dist: inflect (>=0.3.1)
Requires-Dist: numpy (>=1.13.1)
Requires-Dist: nltk (>=3.2.4)
